pandasmemuc/README.MD
pandasmemuc/__init__.py
pandasmemuc/requirements.txt
pandasmemuc/thirdparty.json
pandasmemuc-0.15.dist-info/LICENSE.rst
pandasmemuc-0.15.dist-info/METADATA
pandasmemuc-0.15.dist-info/WHEEL
pandasmemuc-0.15.dist-info/top_level.txt
pandasmemuc-0.15.dist-info/RECORD
