Metadata-Version: 2.1
Name: pandasmemuc
Version: 0.15
Summary: Automating memu emulator with pandas
Home-page: https://github.com/hansalemaos/pandasmemuc
Author: Johannes Fischer
Author-email: aulasparticularesdealemaosp@gmail.com
License: MIT
Keywords: memu,memnuc,pandas
Classifier: Development Status :: 4 - Beta
Classifier: Programming Language :: Python :: 3 :: Only
Classifier: Programming Language :: Python :: 3.10
Classifier: Topic :: Software Development :: Libraries :: Python Modules
Classifier: Topic :: Utilities
License-File: LICENSE.rst
Requires-Dist: PrettyColorPrinter
Requires-Dist: a-pandas-ex-apply-ignore-exceptions
Requires-Dist: a-pandas-ex-xml2df
Requires-Dist: adbkit
Requires-Dist: flexible-partial
Requires-Dist: isiter
Requires-Dist: pandas
Requires-Dist: regex
Requires-Dist: reggisearch
Requires-Dist: requests
Requires-Dist: subprocesskiller
Requires-Dist: touchtouch
